LICENSE
README.md
setup.py
CodeEase.egg-info/PKG-INFO
CodeEase.egg-info/SOURCES.txt
CodeEase.egg-info/dependency_links.txt
CodeEase.egg-info/requires.txt
CodeEase.egg-info/top_level.txt
codeease/__init__.py
codeease/json类.py
codeease/异常类.py
codeease/快速文本类.py
codeease/时间类.py
codeease/编码转换类.py
codeease/访问类.py
tests/__init__.py
tests/test_translator.py